atomate2/__init__.py
atomate2/_version.py
atomate2/py.typed
atomate2/settings.py
atomate2/abinit/__init__.py
atomate2/abinit/files.py
atomate2/abinit/powerups.py
atomate2/abinit/run.py
atomate2/abinit/flows/__init__.py
atomate2/abinit/flows/core.py
atomate2/abinit/jobs/__init__.py
atomate2/abinit/jobs/base.py
atomate2/abinit/jobs/core.py
atomate2/abinit/schemas/__init__.py
atomate2/abinit/schemas/calculation.py
atomate2/abinit/schemas/task.py
atomate2/abinit/sets/__init__.py
atomate2/abinit/sets/base.py
atomate2/abinit/sets/core.py
atomate2/abinit/utils/__init__.py
atomate2/abinit/utils/common.py
atomate2/abinit/utils/history.py
atomate2/abinit/utils/settings.py
atomate2/aims/__init__.py
atomate2/aims/files.py
atomate2/aims/run.py
atomate2/aims/flows/__init__.py
atomate2/aims/flows/anharmonicity.py
atomate2/aims/flows/core.py
atomate2/aims/flows/elastic.py
atomate2/aims/flows/eos.py
atomate2/aims/flows/gw.py
atomate2/aims/flows/phonons.py
atomate2/aims/jobs/__init__.py
atomate2/aims/jobs/base.py
atomate2/aims/jobs/convergence.py
atomate2/aims/jobs/core.py
atomate2/aims/jobs/magnetism.py
atomate2/aims/jobs/phonons.py
atomate2/aims/schemas/__init__.py
atomate2/aims/schemas/calculation.py
atomate2/aims/schemas/task.py
atomate2/aims/utils/__init__.py
atomate2/aims/utils/bands.py
atomate2/aims/utils/common.py
atomate2/aims/utils/units.py
atomate2/amset/__init__.py
atomate2/amset/files.py
atomate2/amset/jobs.py
atomate2/amset/run.py
atomate2/amset/schemas.py
atomate2/ase/__init__.py
atomate2/ase/jobs.py
atomate2/ase/md.py
atomate2/ase/neb.py
atomate2/ase/schemas.py
atomate2/ase/utils.py
atomate2/cli/__init__.py
atomate2/cli/dev.py
atomate2/common/__init__.py
atomate2/common/files.py
atomate2/common/powerups.py
atomate2/common/utils.py
atomate2/common/analysis/__init__.py
atomate2/common/analysis/elastic.py
atomate2/common/builders/__init__.py
atomate2/common/builders/magnetism.py
atomate2/common/flows/__init__.py
atomate2/common/flows/anharmonicity.py
atomate2-0.0.23.dist-info/licenses/LICENSE
atomate2-0.0.23.dist-info/METADATA
atomate2-0.0.23.dist-info/WHEEL
atomate2-0.0.23.dist-info/entry_points.txt
atomate2-0.0.23.dist-info/top_level.txt
atomate2-0.0.23.dist-info/RECORD
